fastapi_query_tools/__init__.py
fastapi_query_tools/dependencies.py
fastapi_query_tools/enums.py
fastapi_query_tools/models.py
fastapi_query_tools/sqlalchemy_ext/__init__.py
fastapi_query_tools/sqlalchemy_ext/utils.py
fastapi_query_tools-1.0.7.dist-info/METADATA
fastapi_query_tools-1.0.7.dist-info/WHEEL
fastapi_query_tools-1.0.7.dist-info/licenses/LICENSE
fastapi_query_tools-1.0.7.dist-info/RECORD
