Metadata-Version: 2.3
Name: fastapi_query_tools
Version: 1.0.7
Summary: A package to simplify filtering and sorting in FastAPI
Project-URL: Homepage, https://github.com/dev-youngstown/fastapi-query-tools
Project-URL: Issues, https://github.com/dev-youngstown/fastapi-query-tools/issues
Author-email: Nicolas Ott <nicobox2002@gmail.com>
License-File: LICENSE
Classifier: License :: OSI Approved :: MIT License
Classifier: Operating System :: OS Independent
Classifier: Programming Language :: Python :: 3
Requires-Python: >=3.10
Requires-Dist: fastapi>=0.110.0
Requires-Dist: pydantic>=2.7.4
Requires-Dist: sqlalchemy>=2.0
